pdf_ingest/__init__.py
pdf_ingest/cli.py
pdf_ingest/cli_docker.py
pdf_ingest/json_util.py
pdf_ingest/language_detection.py
pdf_ingest/scan_and_convert.py
pdf_ingest/types.py
pdf_ingest/win_mount.py
pdf_ingest/parsers/djvu.py
pdf_ingest/parsers/epub.py
pdf_ingest/parsers/fb2.py
pdf_ingest/parsers/pdf.py
pdf_ingest-1.0.13.dist-info/METADATA
pdf_ingest-1.0.13.dist-info/WHEEL
pdf_ingest-1.0.13.dist-info/entry_points.txt
pdf_ingest-1.0.13.dist-info/top_level.txt
pdf_ingest-1.0.13.dist-info/RECORD
