Metadata-Version: 2.4
Name: pdf_ingest
Version: 1.0.13
Summary: PDF Ingester
License: BSD 3-Clause License
Keywords: template-python-cmd
Classifier: Programming Language :: Python :: 3
Requires-Python: >=3.11
Requires-Dist: langdetect
Requires-Dist: epub-utils==0.0.0a5
Requires-Dist: fb2reader==1.0.3
